my_shell_script.py
my_shell_script-0.1.dist-info/METADATA
my_shell_script-0.1.dist-info/WHEEL
my_shell_script-0.1.dist-info/top_level.txt
my_shell_script-0.1.dist-info/RECORD
