Metadata-Version: 2.1
Name: my-shell-script
Version: 0.1
Summary: A Python package that contains a shell script.
